{
  "coreData": {
    "name": "gold",
    "chickenType": "VANILLA",
    "hasFeather": true
  },
  "renderData": {
    "isGlowing": false,
    "hasGlint": false,
    "colorData": {
      "spawnEggPrimaryColor": "#8C8C8C",
      "spawnEggSecondaryColor": "#FAEC53"
    }
  },
  "breedData": {
    "canBreed": false,
    "totalBreedTime": 2400,
    "parent1": "",
    "parent2": ""
  },
  "roostData": {
    "canRoost": false,
    "totalRoostTime": 300,
    "roostOutput": [
      {
        "itemOutput": {
          "id": "minecraft:gold_ingot",
          "minAmount": 1,
          "maxAmount" : 3
        },
        "chance": 1.0
      }
    ]
  }
}